ansys/api/speos/__init__.py
ansys/api/speos/_version.py
ansys/api/speos/grpc_stub.py
ansys/api/speos/LTF/v1/LTF.proto
ansys/api/speos/LTF/v1/LTF_pb2.py
ansys/api/speos/LTF/v1/LTF_pb2.pyi
ansys/api/speos/LTF/v1/LTF_pb2_grpc.py
ansys/api/speos/LTF/v1/LTF_pb2_grpc.pyi
ansys/api/speos/bsdf/v1/anisotropic_bsdf.proto
ansys/api/speos/bsdf/v1/anisotropic_bsdf_pb2.py
ansys/api/speos/bsdf/v1/anisotropic_bsdf_pb2.pyi
ansys/api/speos/bsdf/v1/anisotropic_bsdf_pb2_grpc.py
ansys/api/speos/bsdf/v1/anisotropic_bsdf_pb2_grpc.pyi
ansys/api/speos/bsdf/v1/bsdf_creation.proto
ansys/api/speos/bsdf/v1/bsdf_creation_pb2.py
ansys/api/speos/bsdf/v1/bsdf_creation_pb2.pyi
ansys/api/speos/bsdf/v1/bsdf_creation_pb2_grpc.py
ansys/api/speos/bsdf/v1/bsdf_creation_pb2_grpc.pyi
ansys/api/speos/bsdf/v1/spectral_bsdf.proto
ansys/api/speos/bsdf/v1/spectral_bsdf_pb2.py
ansys/api/speos/bsdf/v1/spectral_bsdf_pb2.pyi
ansys/api/speos/bsdf/v1/spectral_bsdf_pb2_grpc.py
ansys/api/speos/bsdf/v1/spectral_bsdf_pb2_grpc.pyi
ansys/api/speos/common/v1/data.proto
ansys/api/speos/common/v1/data_pb2.py
ansys/api/speos/common/v1/data_pb2.pyi
ansys/api/speos/common/v1/data_pb2_grpc.py
ansys/api/speos/common/v1/data_pb2_grpc.pyi
ansys/api/speos/file/v1/file_transfer.proto
ansys/api/speos/file/v1/file_transfer.py
ansys/api/speos/file/v1/file_transfer_pb2.py
ansys/api/speos/file/v1/file_transfer_pb2.pyi
ansys/api/speos/file/v1/file_transfer_pb2_grpc.py
ansys/api/speos/file/v1/file_transfer_pb2_grpc.pyi
ansys/api/speos/intensity/v1/intensity.proto
ansys/api/speos/intensity/v1/intensity_pb2.py
ansys/api/speos/intensity/v1/intensity_pb2.pyi
ansys/api/speos/intensity/v1/intensity_pb2_grpc.py
ansys/api/speos/intensity/v1/intensity_pb2_grpc.pyi
ansys/api/speos/intensity_distributions/v1/base_map_template.proto
ansys/api/speos/intensity_distributions/v1/base_map_template_pb2.py
ansys/api/speos/intensity_distributions/v1/base_map_template_pb2.pyi
ansys/api/speos/intensity_distributions/v1/base_map_template_pb2_grpc.py
ansys_api_speos-0.16.0.dist-info/licenses/AUTHORS
ansys_api_speos-0.16.0.dist-info/licenses/LICENSE
ansys_api_speos-0.16.0.dist-info/METADATA
ansys_api_speos-0.16.0.dist-info/WHEEL
ansys_api_speos-0.16.0.dist-info/entry_points.txt
ansys_api_speos-0.16.0.dist-info/top_level.txt
ansys_api_speos-0.16.0.dist-info/RECORD
