Metadata-Version: 2.4
Name: ansys-api-speos
Version: 0.16.0
Summary: Autogenerated python gRPC interface package for ansys-api-speos, built on 09:16:54 on 15 December 2025
Home-page: https://github.com/ansys/ansys-api-speos
Author: ANSYS, Inc.
Author-email: pyansys.core@ansys.com
License: MIT
Project-URL: Documentation, https://github.com/ansys/ansys-api-speos/#readme
Project-URL: Source, https://github.com/ansys/ansys-api-speos/
Project-URL: Tracker, https://github.com/ansys/ansys-api-speos/issues/
Requires-Python: >=3.10
License-File: LICENSE
License-File: AUTHORS
Requires-Dist: grpcio~=1.48
Requires-Dist: protobuf<7,>=3.20
Dynamic: author
Dynamic: author-email
Dynamic: description
Dynamic: description-content-type
Dynamic: home-page
Dynamic: license
Dynamic: license-file
Dynamic: project-url
Dynamic: requires-dist
Dynamic: requires-python
Dynamic: summary
